{
    "id": 1351,
    "source": "barnes",
    "verse_id": 18258,
    "verse_count": 1,
    "reference": "31:7 ",
    "title": "",
    "html": "<p><em>For in that day<\/em>&mdash;That is, in the invasion of Sennacherib, and the events that shalt be consequent thereon.<\/p><p><em>Every man shall cast away his idols<\/em>&mdash;(see the note at <a class=\"isa\" verses=\"MTgyNDA=\">Isaiah 30:22<\/a> ; compare the note at <a class=\"isa\" verses=\"MTc3MDY=\">Isaiah 2:20<\/a>).<\/p><p><em>For a sin<\/em>&mdash;Or rather, the sin which your own hands have made. The sense is, that the making of those idols had been a sin, or sin itself. It had been &ldquo;the&rdquo; sin, by way of eminence, which was chargeable upon them.<\/p>",
    "audit": 1
}