{
    "id": 9308,
    "source": "benson",
    "verse_id": 18283,
    "verse_count": 2,
    "reference": "33:3\u20134",
    "title": "",
    "html": " <p> <a class=\"isa\" verses=\"eyIxODI4MyI6Mn0=\">Isaiah 33:3-4<\/a>. <i>At the noise of the tumult <\/i>\u2014Which shall be made upon the angel\u2019s destroying the army; <i>the people fled <\/i>\u2014Namely, those of the army who escaped that stroke. <i>At the lifting up of thyself <\/i>\u2014To execute judgment; <i>the nations were scattered <\/i>\u2014The people of divers nations which made up Sennacherib\u2019s army. <i>And your spoil <\/i>\u2014That treasure which you have raked together by spoiling divers people; <i>shall be gathered <\/i>\u2014By the Jews at Jerusalem, when you shall be forced to flee away with all possible speed, leaving your spoils behind you; <i>like the gathering of the caterpillar <\/i>\u2014As caterpillars gather and devour all the fruits of the earth, which was a common plague in those countries; <i>as the running to and fro of locusts, <\/i> &c.\u2014As locusts, especially when they are armed by commission from God, come with great force, and run hither and thither devouring every thing before them; <i>shall he run upon them <\/i>\u2014Namely, Hezekiah, with his people, shall thus eagerly run to the spoil of the Assyrian camp, and shall take it. <\/p> ",
    "audit": null
}