{
    "id": 9533,
    "source": "benson",
    "verse_id": 18801,
    "verse_count": 1,
    "reference": "58:14",
    "title": "",
    "html": "<p><a class=\"isa\" verses=\"WzE4ODAxXQ==\">Isaiah 58:14<\/a><em>.<\/em><i>Then shalt thou delight thyself in the Lord <\/i>\u2014 This refers to the preceding verse, as if he had said, If thou wilt delight thyself in the sabbath, then thou shalt delight in the God of the sabbath, namely, in his goodness and faithfulness to thee, and in the assurance of his love and favour. <i>I will cause thee to ride, <\/i>&c. \u2014 Thou shalt be above the reach of danger. <i>And feed thee with the heritage of Jacob <\/i>\u2014 Thou shalt enjoy the good of the land of Canaan, which God promised as a heritage to Jacob and his seed, <a class=\"ref\">Genesis 35:12<\/a>. Or, figuratively understood, thou shalt enjoy temporal as well as spiritual blessings. The Lord will withhold from thee no manner of thing which he sees to be for thy prosperity and happiness. <i>For the mouth of the Lord hath spoken it <\/i>\u2014 The promise is sure, and shall infallibly be fulfilled, having proceeded from the mouth of him who cannot lie. <\/p>",
    "audit": null
}