{
    "id": 16932,
    "source": "brewster",
    "verse_id": 17900,
    "verse_count": 2,
    "reference": "11:15\u201316",
    "title": "",
    "html": "<p><b><a class=\"ref\">2 Nephi 21:15-16<\/a><\/b><\/p>     <p>Even as God showed forth his power against ancient Egypt at the time of the Exodus, so shall He provide divine intervention during the gathering of the last days. He will perform modern miracles in order to accomplish His purposes.<\/p>     <table>         <tbody>             <tr>                 <td>15 And the Lord shall utterly destroy the tongue of the Egyptian sea; and with his mighty wind shall he shake his hand over the river, and shall smite it in the seven streams, and make men go over <i>dryshod.<\/i>                     <br>                     <br>16 And there shall be <i>an<\/i> highway for the remnant of his people<u>,<\/u> which shall be left, from Assyria<u>;<\/u> like as it was to Israel in the day that he came up out of the land of Egypt.                     <br>                 <\/td>                 <td>15 And the Lord shall utterly destroy the tongue of the Egyptian sea; and with his mighty wind he shall shake his hand over the river, and shall smite it in the seven streams, and make men go over <i>dry shod.<\/i>                     <br>                     <br>16 And there shall be <i>a<\/i> highway for the remnant of his people which shall be left, from Assyria<u>,<\/u> like as it was to Israel in the day that he came up out of the land of Egypt.                     <br>                 <\/td>             <\/tr>         <\/tbody>     <\/table>",
    "audit": null
}