{
    "id": 17127,
    "source": "brewster",
    "verse_id": 18666,
    "verse_count": 1,
    "reference": "50:3",
    "title": "",
    "html": "<p><b>(<a class=\"ref\">2 Nephi 7:3<\/a>).<\/b>\"<i>Clothe the heavens with blackness, and I make sackcloth their covering.<\/i>\" One of the plagues the Lord inflicted on Pharaoh's Egypt was to cover the land with darkness. (<a class=\"ref\">Exodus 10:21-23<\/a>.) Footnote references in the Book of Mormon text identify <a class=\"ref\">Revelation 6:12<\/a> as a possible future fulfillment of this prophecy, when \"the sun [shall become] black as sackcloth.\" (See also <a class=\"ref\">Matthew 24:29; D&amp;C 45:42<\/a>; BICQ, 183-85.) Sackcloth is a coarse fabric of a dark color and was used in making the garments worn by mourners.<\/p>",
    "audit": null
}