{
    "id": 17061,
    "source": "brewster",
    "verse_id": 18619,
    "verse_count": 1,
    "reference": "48:4",
    "title": "",
    "html": "<p><b>(<a class=\"ref\">1 Nephi 20:4<\/a>).<\/b>\"<i>Thy neck is an iron sinew, and thy brow brass.<\/i>\" In more modern terminology the obstinate or stubborn of Israel could be described as having necks that would not turn they were <i>stiffnecked;<\/i> and their minds were not pliant to the promptings of the Spirit they were <i>hardheaded.<\/i> A stiff neck does not turn in the direction of divine guidance. By contrast, the Lord promises to \"feel after\" those who \"stiffen not their necks.\" (<a class=\"ref\">D&amp;C 112:13<\/a>.)<\/p>",
    "audit": null
}