{
    "id": 17118,
    "source": "brewster",
    "verse_id": 18662,
    "verse_count": 1,
    "reference": "49:25",
    "title": "",
    "html": "<p><b>(<a class=\"ref\">1 Nephi 21:25; 2 Nephi 6:17<\/a>).<\/b>\"<i>I will contend with him that contendeth with thee.<\/i>\" \"For behold, I do not require at their hands to fight the battles of Zion; for, as I said in a former commandment, even so will I fulfil I will fight your battles.\" (<a class=\"ref\">D&amp;C 105:14<\/a>.)<\/p>",
    "audit": null
}