{
    "id": 16081,
    "source": "btw",
    "verse_id": 17886,
    "verse_count": 5,
    "reference": "11:1\u20135",
    "title": "The Stem of Jesse",
    "html": "  <p>  <b>2 Nephi 21:1. \"Stem of Jesse\" <\/b>Other translations refer to the \"stump\" of Jesse rather than stem. Interestingly, after the Lord has cut down a wicked forest, a new shoot develops from which will come the rod. Modern revelation gives us his identity: \"Who is the Stem of Jesse? . . . Verily thus saith the Lord: It is Christ\" (D&amp;C 113:1\u20132).  <\/p>  ",
    "audit": null
}