{
    "id": 9783,
    "source": "bullinger",
    "verse_id": 17842,
    "verse_count": 1,
    "reference": "9:12",
    "title": "",
    "html": "<p><em>For all this, &c.<\/em> See note on <a class=\"isa\" verses=\"MTc3NjY=\">Isaiah 5:26<\/a>. Note the Figure of speech <i>Amoeboeon<\/i>, <a class=\"isa\" verses=\"MTc3NjU=\">Isaiah 5:25<\/a>; here, verses: <a class=\"isa\" verses=\"MTc4NDc=\">Isaiah 9:17<\/a>, <a class=\"isa\" verses=\"MTc4NTE=\">Isaiah 9:21<\/a>, <a class=\"isa\" verses=\"MTc4MzQ=\">Isaiah 9:4<\/a>. stretched out: in judgment. See note on <a class=\"isa\" verses=\"W10=\">Isaiah 6:26<\/a>. <\/p>",
    "audit": null
}