{
    "id": 8441,
    "source": "clarke",
    "verse_id": 18199,
    "verse_count": 1,
    "reference": "29:5",
    "title": "",
    "html": "<p><em>The multitude of thy strangers \"The multitude of the proud\"\u2014<\/em>For <span class=\"greek-hebrew\">\u05d6\u05e8\u05d9\u05da <\/span>   <span class=\"translit\">zarayich<\/span>, thy strangers, read <span class=\"greek-hebrew\">\u05d6\u05d3\u05d9\u05dd <\/span>   <span class=\"translit\">zedim<\/span>, the proud, according to the Septuagint; parallel to and synonymous with <span class=\"greek-hebrew\">\u05e2\u05e8\u05d9\u05e6\u05d9\u05dd <\/span>   <span class=\"translit\">aritsim<\/span>, the terrible, in the next line: the <span class=\"greek-hebrew\">\u05e8 <\/span>   <span class=\"translit\">resh<\/span>  was at first <span class=\"greek-hebrew\">\u05d3 <\/span>   <span class=\"translit\">daleth<\/span>  in a MS. See note on  <a class=\"isa\" verses=\"WzE4MTIxXQ==\">Isaiah 25:2<\/a>.<\/p>\n\n<p>The fifth, sixth, and seventh verses contain an admirable description of the destruction of Sennacherib's army, with a beautiful variety of the most expressive and sublime images: perhaps more adapted to show the greatness, the suddenness, and horror of the event, than the means and manner by which it was effected. Compare  <a class=\"isa\" verses=\"eyIxODI0OCI6NH0=\">Isaiah 30:30-33<\/a>.<\/p>",
    "audit": null
}