{
    "id": 14351,
    "source": "hcc",
    "verse_id": 18786,
    "verse_count": 1,
    "reference": "57:20",
    "title": "",
    "html": "<p><i>Dirt.<\/i>  Literally, \"treading,\" <i>conculcationem.<\/i>  (Haydock) --- The works of the wicked are fruitless.  They have no content.  (Calmet)\t\tNon enim gaz\u00e6 neque consularis<\/p>\n<p>\t\tSummovet lictor miseros tumultus,<\/p>\n<p>\t\tMentis et curas laqueata circum,<\/p>\n<p>\t\tTecta volantes. ----- (Horace, ii. ode 16.)<\/p>\n<p>--- The obstinate sinner can receive no pardon.  (Worthington)<\/p>\n<p> <span class=\"greek-hebrew\">\u00a0<\/span><\/p>\n<p> <span class=\"greek-hebrew\">\u00a0<\/span><\/p>",
    "audit": null
}