{
    "id": 13019,
    "source": "wen",
    "verse_id": 18541,
    "verse_count": 1,
    "reference": "44:7",
    "title": "",
    "html": "Who\u2014Which of all the Heathen gods. Declare\u2014Shall by his powerful word cause it to be, and by his fore\u2014knowledge declare that it shall be. Set in order\u2014Orderly relate all future events in the same manner as they shall happen. Since\u2014Since I first made man upon earth. The things\u2014Such things as are near at hand, and such as are to come hereafter.",
    "audit": null
}